kausal/__init__.py
kausal/generator.py
kausal/graph.py
kausal/koopman.py
kausal/stats.py
kausal/utils.py
kausal/baselines/__init__.py
kausal/baselines/utils.py
kausal/baselines/gvar/gvar.py
kausal/baselines/neuralgc/neuralgc.py
kausal/baselines/tsci/minimal_example.py
kausal/baselines/tsci/models.py
kausal/baselines/tsci/patched_reci.py
kausal/baselines/tsci/rossler_lorenz_sine_wave.py
kausal/baselines/tsci/rossler_lorenz_vary_C.py
kausal/baselines/tsci/rossler_lorenz_vary_C_comparisons.py
kausal/baselines/tsci/rossler_lorenz_vary_liblength.py
kausal/baselines/tsci/rossler_lorenz_vary_sigma.py
kausal/baselines/tsci/tsci.py
kausal/baselines/tsci/utils.py
kausal/baselines/tsci/latent_tsci/experiments/Dpendulum/get_path.py
kausal/baselines/tsci/latent_tsci/experiments/Dpendulum/gruode_scores.py
kausal/baselines/tsci/latent_tsci/experiments/Dpendulum/run_gruode.py
kausal/baselines/tsci/latent_tsci/latentccm/__init__.py
kausal/baselines/tsci/latent_tsci/latentccm/causal_inf.py
kausal/baselines/tsci/latent_tsci/latentccm/data_utils.py
kausal/baselines/tsci/latent_tsci/latentccm/datagen_utils.py
kausal/baselines/tsci/latent_tsci/latentccm/fitting_models/models.py
kausal/observables/__init__.py
kausal/observables/base.py
kausal/observables/cnn_features.py
kausal/observables/identity_features.py
kausal/observables/mlp_features.py
kausal/observables/polynomial_features.py
kausal/observables/random_fourier_features.py
kausal/observables/time_delay_features.py
kausal/regressors/__init__.py
kausal/regressors/base.py
kausal/regressors/dmd.py
kausal/regressors/nndmd.py
kausal/regressors/pinv.py
kausal-1.0.1.dist-info/licenses/LICENSE.txt
kausal-1.0.1.dist-info/METADATA
kausal-1.0.1.dist-info/WHEEL
kausal-1.0.1.dist-info/top_level.txt
kausal-1.0.1.dist-info/RECORD
