Metadata-Version: 2.4
Name: kausal
Version: 1.0.1
Summary: Deep Koopman operators for causal discovery
Author-email: Juan Nathaniel <jn2808@columbia.edu>
License-Expression: MIT
Project-URL: Homepage, https://github.com/juannat7/kausal
Project-URL: Issues, https://github.com/juannat7/kausal/issues
Classifier: Programming Language :: Python :: 3
Classifier: Operating System :: OS Independent
Requires-Python: >=3.10
License-File: LICENSE.txt
Requires-Dist: benchmark-mi>=0.1.3
Requires-Dist: causal-learn>=0.1.3.8
Requires-Dist: cdt>=0.6.0
Requires-Dist: ipdb>=0.13.13
Requires-Dist: jaxtyping>=0.3.3
Requires-Dist: lingam>=1.9.1
Requires-Dist: matplotlib>=3.10.1
Requires-Dist: networkx>=3.4.2
Requires-Dist: numpy<2.0
Requires-Dist: pandas<2.0
Requires-Dist: parameterfree>=0.0.1
Requires-Dist: scikit-learn>=1.7.2
Requires-Dist: setuptools>=79.0.0
Requires-Dist: skccm>=0.2.dev0
Requires-Dist: statsmodels>=0.14.5
Requires-Dist: tensorly>=0.9.0
Requires-Dist: tigramite>=5.2.7.0
Requires-Dist: torch>=2.6.0
Requires-Dist: torchdiffeq>=0.2.5
Requires-Dist: tqdm>=4.66.5
Requires-Dist: jax<=0.4.33
Requires-Dist: jaxlib<=0.4.33
Requires-Dist: xarray<=2023.10.0
Requires-Dist: netcdf4>=1.7.2
Dynamic: license-file
